markitdown_advanced_pdf_llm/__about__.py
markitdown_advanced_pdf_llm/__init__.py
markitdown_advanced_pdf_llm/_plugin.py
markitdown_advanced_pdf_llm_plugin-0.1.1.dist-info/METADATA
markitdown_advanced_pdf_llm_plugin-0.1.1.dist-info/WHEEL
markitdown_advanced_pdf_llm_plugin-0.1.1.dist-info/entry_points.txt
markitdown_advanced_pdf_llm_plugin-0.1.1.dist-info/licenses/LICENSE
markitdown_advanced_pdf_llm_plugin-0.1.1.dist-info/RECORD
