Metadata-Version: 2.4
Name: markitdown-advanced-pdf-llm-plugin
Version: 0.1.1
Summary: 3-rd party plugin for markitdown library. It is to be used for converting a pdf to markdown purely based on llm's capability
Project-URL: repo, https://github.com/AjjayK/markitdown-advanced-pdf-llm-plugin
Author-email: AjjayK <ajjay.kanna@gmail.com>
License-File: LICENSE
Classifier: Development Status :: 4 - Beta
Classifier: Programming Language :: Python
Classifier: Programming Language :: Python :: 3.10
Classifier: Programming Language :: Python :: 3.11
Classifier: Programming Language :: Python :: 3.12
Classifier: Programming Language :: Python :: 3.13
Classifier: Programming Language :: Python :: Implementation :: CPython
Classifier: Programming Language :: Python :: Implementation :: PyPy
Requires-Python: >=3.10
Requires-Dist: markitdown>=0.1.1
Requires-Dist: pillow>=11.2.1
Requires-Dist: pymupdf>=1.25.0
Requires-Dist: pypdf>=5.4.0
